{
  "gitSyncId": "68fa28cb2b0762607528340c_8aa759a2-c711-4c78-8734-888366088dfa",
  "id": "Inventario_MenuNavUS.allPages",
  "pluginId": "js-plugin",
  "pluginType": "JS",
  "unpublishedAction": {
    "actionConfiguration": {
      "encodeParamsToggle": true,
      "jsArguments": [],
      "paginationType": "NONE",
      "timeoutInMillisecond": 10000
    },
    "collectionId": "Inventario_MenuNavUS",
    "confirmBeforeExecute": false,
    "datasource": {
      "isAutoGenerated": false,
      "name": "UNUSED_DATASOURCE",
      "pluginId": "js-plugin"
    },
    "dynamicBindingPathList": [
      {
        "key": "body"
      }
    ],
    "fullyQualifiedName": "MenuNavUS.allPages",
    "name": "allPages",
    "pageId": "Inventario",
    "runBehaviour": "MANUAL",
    "userSetOnLoad": false
  }
}