{
  "gitSyncId": "68b0fc8d2b07626075282edf_4a6ed8fd-feff-4cbc-a4f0-acfd46aa1628",
  "id": "Pedidos2_Lines.__commit",
  "pluginId": "js-plugin",
  "pluginType": "JS",
  "unpublishedAction": {
    "actionConfiguration": {
      "encodeParamsToggle": true,
      "jsArguments": [
        {
          "name": "next"
        }
      ],
      "paginationType": "NONE",
      "timeoutInMillisecond": 10000
    },
    "collectionId": "Pedidos2_Lines",
    "confirmBeforeExecute": false,
    "datasource": {
      "isAutoGenerated": false,
      "name": "UNUSED_DATASOURCE",
      "pluginId": "js-plugin"
    },
    "dynamicBindingPathList": [
      {
        "key": "body"
      }
    ],
    "fullyQualifiedName": "Lines.__commit",
    "name": "__commit",
    "pageId": "Pedidos2",
    "runBehaviour": "MANUAL",
    "userSetOnLoad": false
  }
}