{
  "gitSyncId": "68fa28cb2b0762607528340c_8ae5dab0-5460-4529-8d80-2efdd0d4a145",
  "id": "Cobros_GetPagos",
  "pluginId": "restapi-plugin",
  "pluginType": "API",
  "unpublishedAction": {
    "actionConfiguration": {
      "autoGeneratedHeaders": [],
      "body": "",
      "bodyFormData": [],
      "encodeParamsToggle": true,
      "formData": {
        "apiContentType": "none"
      },
      "headers": [
        {
          "key": "apikey",
          "value": "eyJhbGciOiJIUzI1NiIsInR5cCI6IkpXVCJ9.eyJpc3MiOiJzdXBhYmFzZSIsInJlZiI6ImFreHJkcXZpandncnd0dGFzbXVrIiwicm9sZSI6ImFub24iLCJpYXQiOjE3NTY1MTM0NzQsImV4cCI6MjA3MjA4OTQ3NH0.71Oe8LUDrw_fTYbaWaLRxYDK9xOaAL1M3AZfY5ldfH4"
        },
        {
          "key": "Authorization",
          "value": "Bearer {{ appsmith.store.access_token }}"
        }
      ],
      "httpMethod": "GET",
      "httpVersion": "HTTP11",
      "paginationType": "NONE",
      "path": "/rest/v1/m10_pagos",
      "pluginSpecifiedTemplates": [
        {
          "value": true
        }
      ],
      "queryParameters": [
        {
          "key": "select",
          "value": "*"
        },
        {
          "key": "order",
          "value": "id_aplicacion_pago.asc"
        }
      ],
      "timeoutInMillisecond": 10000
    },
    "confirmBeforeExecute": false,
    "datasource": {
      "datasourceConfiguration": {
        "url": "https://akxrdqvijwgrwttasmuk.supabase.co"
      },
      "isAutoGenerated": false,
      "name": "DEFAULT_REST_DATASOURCE",
      "pluginId": "restapi-plugin"
    },
    "dynamicBindingPathList": [
      {
        "key": "headers[1].value"
      }
    ],
    "name": "GetPagos",
    "pageId": "Cobros",
    "runBehaviour": "AUTOMATIC",
    "userSetOnLoad": true
  }
}