{
  "gitSyncId": "68fa28cb2b0762607528340c_6c4d2c65-8b92-40d2-ba57-26688bc4fa66",
  "id": "Cobros_InsertClientes",
  "pluginId": "restapi-plugin",
  "pluginType": "API",
  "unpublishedAction": {
    "actionConfiguration": {
      "autoGeneratedHeaders": [
        {
          "key": "content-type",
          "value": "application/json"
        }
      ],
      "body": "{\n  \"_id_cliente\": null,\n  \"_nombre_cliente\": {{ input_one_new.text || null }},\n  \"_nivel_cliente\": null,\n  \"_lista_negra\": {{ switch_one_new.isSwitchedOn || null }},\n  \"_celular_cliente\": {{ celular_cliente_new.text ? Number(celular_cliente_new.text) : null }},\n  \"_email_cliente\": {{ input_two_new.text || null }},\n  \"_razon_social\": {{ input_five_new.text || null }},\n  \"_rfc_facturacion\": {{ input_six_new.text || null }},\n  \"_comentario_cliente\": {{ input_three_new.text || null }},\n  \"_regimen_fiscal\": {{ select_two_new.selectedOptionValue || null }},\n  \"_uso_de_cfdi\": {{ select_three_new.selectedOptionValue || null }},\n  \"_id_cotizacion\": null,\n  \"_prefijo_nombre_cliente\": {{ select_seven_new.selectedOptionValue || null }},\n  \"_tipo_cliente\": {{ select_one_new.selectedOptionValue || null }},\n  \"_requiere_factura\": {{ switch_one_new.isSwitchedOn }},\n  \"_estatus_cliente\": {{ estatus_cliente.text || null }},\n  \"_dia_de_corte\": {{ select_six_new.selectedOptionValue ? Number(select_six_new.selectedOptionValue) : null }},\n  \"_forma_de_pago\": {{ select_four_new.selectedOptionValue || null }},\n  \"_domicilio_fiscal\": {{ input_nine_new.text || null }},\n  \"_comodin_a\": {{ input_seven_new.text || null }},\n  \"_comodin_b\": {{ select_five_new.selectedOptionValue || null }},\n  \"_comodin_c\": {{ input_eight_new.text || null }},\n  \"_comodin_d\": null,\n  \"_comodin_e\": null\n}",
      "bodyFormData": [],
      "encodeParamsToggle": true,
      "formData": {
        "apiContentType": "application/json"
      },
      "headers": [
        {
          "key": "Authorization",
          "value": "Bearer {{ appsmith.store.access_token }}"
        },
        {
          "key": "apikey",
          "value": "eyJhbGciOiJIUzI1NiIsInR5cCI6IkpXVCJ9.eyJpc3MiOiJzdXBhYmFzZSIsInJlZiI6ImFreHJkcXZpandncnd0dGFzbXVrIiwicm9sZSI6ImFub24iLCJpYXQiOjE3NTY1MTM0NzQsImV4cCI6MjA3MjA4OTQ3NH0.71Oe8LUDrw_fTYbaWaLRxYDK9xOaAL1M3AZfY5ldfH4"
        }
      ],
      "httpMethod": "POST",
      "httpVersion": "HTTP11",
      "paginationType": "NONE",
      "path": "/rest/v1/rpc/m05_clientes_insert_min",
      "pluginSpecifiedTemplates": [
        {
          "value": true
        }
      ],
      "queryParameters": [],
      "timeoutInMillisecond": 100000
    },
    "confirmBeforeExecute": false,
    "datasource": {
      "datasourceConfiguration": {
        "url": "https://akxrdqvijwgrwttasmuk.supabase.co"
      },
      "isAutoGenerated": false,
      "name": "DEFAULT_REST_DATASOURCE",
      "pluginId": "restapi-plugin"
    },
    "dynamicBindingPathList": [
      {
        "key": "headers[0].value"
      },
      {
        "key": "body"
      }
    ],
    "name": "InsertClientes",
    "pageId": "Cobros",
    "runBehaviour": "MANUAL",
    "userSetOnLoad": false
  }
}