{
  "gitSyncId": "68b0fc8d2b07626075282edf_7e548119-1568-4cf9-94c3-c2da9f669e33",
  "id": "DashboardGral_avg_feed_sales",
  "pluginId": "postgres-plugin",
  "pluginType": "DB",
  "unpublishedAction": {
    "actionConfiguration": {
      "body": "SELECT AVG(rating) FROM showroom_db;",
      "encodeParamsToggle": true,
      "paginationType": "NONE",
      "pluginSpecifiedTemplates": [
        {
          "value": true
        }
      ],
      "timeoutInMillisecond": 10000
    },
    "confirmBeforeExecute": false,
    "datasource": {
      "id": "Sample Database",
      "isAutoGenerated": false,
      "name": "Sample Database",
      "pluginId": "postgres-plugin"
    },
    "dynamicBindingPathList": [],
    "name": "avg_feed_sales",
    "pageId": "DashboardGral",
    "runBehaviour": "ON_PAGE_LOAD",
    "userSetOnLoad": false
  }
}