{
  "accentColor": "{{appsmith.theme.colors.primaryColor}}",
  "animateLoading": true,
  "autoFocus": false,
  "borderRadius": "{{appsmith.theme.borderRadius.appBorderRadius}}",
  "bottomRow": 17,
  "boxShadow": "none",
  "defaultText": "{{\n  es_cliente_existente.isSwitchedOn\n    ? (appsmith.store.clienteSel?.id_cliente || \"\")\n    : \"\"\n}}\n",
  "dynamicBindingPathList": [
    {
      "key": "accentColor"
    },
    {
      "key": "borderRadius"
    },
    {
      "key": "defaultText"
    },
    {
      "key": "isDisabled"
    }
  ],
  "dynamicHeight": "FIXED",
  "dynamicPropertyPathList": [
    {
      "key": "isDisabled"
    }
  ],
  "dynamicTriggerPathList": [],
  "iconAlign": "left",
  "inputType": "TEXT",
  "isDisabled": "{{ true }}\n",
  "isLoading": false,
  "isRequired": false,
  "isVisible": true,
  "key": "h4sporpdly",
  "label": "ID cliente",
  "labelAlignment": "left",
  "labelPosition": "Top",
  "labelStyle": "BOLD",
  "labelTextColor": "#231f20",
  "labelTextSize": "1rem",
  "labelWidth": 5,
  "leftColumn": 54,
  "maxDynamicHeight": 9000,
  "minDynamicHeight": 4,
  "minWidth": 450,
  "mobileBottomRow": 55,
  "mobileLeftColumn": 2,
  "mobileRightColumn": 22,
  "mobileTopRow": 48,
  "needsErrorInfo": false,
  "originalBottomRow": 17,
  "originalTopRow": 10,
  "parentColumnSpace": 12.6875,
  "parentId": "t6m6k5xey8",
  "parentRowSpace": 10,
  "renderMode": "CANVAS",
  "resetOnSubmit": true,
  "responsiveBehavior": "fill",
  "rightColumn": 62,
  "showStepArrows": false,
  "topRow": 10,
  "type": "INPUT_WIDGET_V2",
  "version": 2,
  "widgetId": "lyjy37myd3",
  "widgetName": "id_cliente"
}