{
  "gitSyncId": "691f7e1c2b076260752839dd_921f893d-c9de-4f80-89a1-63a7e6fa1651",
  "id": "Dashboard General_OperacionDia.totalSinListaNegra",
  "pluginId": "js-plugin",
  "pluginType": "JS",
  "unpublishedAction": {
    "actionConfiguration": {
      "encodeParamsToggle": true,
      "jsArguments": [],
      "paginationType": "NONE",
      "timeoutInMillisecond": 10000
    },
    "collectionId": "Dashboard General_OperacionDia",
    "confirmBeforeExecute": false,
    "datasource": {
      "isAutoGenerated": false,
      "name": "UNUSED_DATASOURCE",
      "pluginId": "js-plugin"
    },
    "dynamicBindingPathList": [
      {
        "key": "body"
      }
    ],
    "fullyQualifiedName": "OperacionDia.totalSinListaNegra",
    "name": "totalSinListaNegra",
    "pageId": "Dashboard General",
    "runBehaviour": "MANUAL",
    "userSetOnLoad": false
  }
}